{
  "version": 1,
  "id": "knight",
  "direction_set": "4-way",
  "sheets": [
    {
      "animation": "idle",
      "direction": "north",
      "timeline_id": "knight-idle-north",
      "flip": null,
      "frame_count": 2,
      "frame_rects": [
        {
          "id": "idle-north-1",
          "x": 0,
          "y": 0,
          "width": 32,
          "height": 32
        },
        {
          "id": "idle-north-2",
          "x": 32,
          "y": 0,
          "width": 32,
          "height": 32
        }
      ],
      "frame_digests": [
        "1c1a643658181ace6038484261bc51ef45b8fe990a5511e45c5fd9faaeec397a",
        "ac8b1fcb4a2ba0e1d64c8b9464c2e61ef56831a6d8758a280d3d9141c6c2c896"
      ],
      "sheet_digest": "5dc7b8b7cdadbd2b89b5ac7789bdee3f812a5b5f7bc9de893e45e491fd342416",
      "phaser_load": {
        "key": "knight-idle-north",
        "url": "asset.svg",
        "svgConfig": {
          "width": 128,
          "height": 32
        }
      }
    },
    {
      "animation": "idle",
      "direction": "south",
      "timeline_id": "knight-idle-south",
      "flip": null,
      "frame_count": 2,
      "frame_rects": [
        {
          "id": "idle-south-1",
          "x": 0,
          "y": 0,
          "width": 32,
          "height": 32
        },
        {
          "id": "idle-south-2",
          "x": 32,
          "y": 0,
          "width": 32,
          "height": 32
        }
      ],
      "frame_digests": [
        "1c1a643658181ace6038484261bc51ef45b8fe990a5511e45c5fd9faaeec397a",
        "ac8b1fcb4a2ba0e1d64c8b9464c2e61ef56831a6d8758a280d3d9141c6c2c896"
      ],
      "sheet_digest": "de455705b6e37bc5d233f6bf0888b7d14aeae7ee4ab523cc0cbf8909135d028e",
      "phaser_load": {
        "key": "knight-idle-south",
        "url": "asset.svg",
        "svgConfig": {
          "width": 128,
          "height": 32
        }
      }
    },
    {
      "animation": "idle",
      "direction": "east",
      "timeline_id": "knight-idle-east",
      "flip": null,
      "frame_count": 2,
      "frame_rects": [
        {
          "id": "idle-east-1",
          "x": 0,
          "y": 0,
          "width": 32,
          "height": 32
        },
        {
          "id": "idle-east-2",
          "x": 32,
          "y": 0,
          "width": 32,
          "height": 32
        }
      ],
      "frame_digests": [
        "1c1a643658181ace6038484261bc51ef45b8fe990a5511e45c5fd9faaeec397a",
        "ac8b1fcb4a2ba0e1d64c8b9464c2e61ef56831a6d8758a280d3d9141c6c2c896"
      ],
      "sheet_digest": "8ef6015930bf9edc6cc2df8111351f2fbcc3fa3deb048580cc7ea13a370755a9",
      "phaser_load": {
        "key": "knight-idle-east",
        "url": "asset.svg",
        "svgConfig": {
          "width": 128,
          "height": 32
        }
      }
    },
    {
      "animation": "idle",
      "direction": "west",
      "timeline_id": "knight-idle-west",
      "flip": "horizontal",
      "frame_count": 2,
      "frame_rects": [
        {
          "id": "idle-west-1",
          "x": 0,
          "y": 0,
          "width": 32,
          "height": 32
        },
        {
          "id": "idle-west-2",
          "x": 32,
          "y": 0,
          "width": 32,
          "height": 32
        }
      ],
      "frame_digests": [
        "df2e0fc5e9a151f47d2a13ab7ad23eb75a2969fd4a3e9b079c41f1acf6486a15",
        "150f6110cffe500419f3d15b4c0b6602531b4da82e99cb9b6719cb3d83c90634"
      ],
      "sheet_digest": "7152bcb7b5684ea32ca45251b7cbbf45615670d94d58074fe5e3345d0ce9e91b",
      "phaser_load": {
        "key": "knight-idle-west",
        "url": "asset.svg",
        "svgConfig": {
          "width": 128,
          "height": 32
        }
      }
    },
    {
      "animation": "walk",
      "direction": "north",
      "timeline_id": "knight-walk-north",
      "flip": null,
      "frame_count": 4,
      "frame_rects": [
        {
          "id": "walk-north-1",
          "x": 0,
          "y": 0,
          "width": 32,
          "height": 32
        },
        {
          "id": "walk-north-2",
          "x": 32,
          "y": 0,
          "width": 32,
          "height": 32
        },
        {
          "id": "walk-north-3",
          "x": 64,
          "y": 0,
          "width": 32,
          "height": 32
        },
        {
          "id": "walk-north-4",
          "x": 96,
          "y": 0,
          "width": 32,
          "height": 32
        }
      ],
      "frame_digests": [
        "3d49e191b17d44c011c93252129e2ac896d09e1febba8b7f74779867153228bb",
        "43d61b2592551863ec83b0a1ad9032d5c7c93e139ec3a6b0821d6e4ce1c2ba24",
        "d36e3947fac0a7e184a9bab47f069f18a8e5c40499db7a608e3cd3c271ff045b",
        "8ee3eebc032dee3d13370f626cae1b691f6b86a61c2ad89fbd60844c913b57df"
      ],
      "sheet_digest": "52172739e17cc8d4ed04080eb4986cbfa4c018934de80e0dd56157fa4784aa04",
      "phaser_load": {
        "key": "knight-walk-north",
        "url": "asset.svg",
        "svgConfig": {
          "width": 128,
          "height": 32
        }
      }
    },
    {
      "animation": "walk",
      "direction": "south",
      "timeline_id": "knight-walk-south",
      "flip": null,
      "frame_count": 4,
      "frame_rects": [
        {
          "id": "walk-south-1",
          "x": 0,
          "y": 0,
          "width": 32,
          "height": 32
        },
        {
          "id": "walk-south-2",
          "x": 32,
          "y": 0,
          "width": 32,
          "height": 32
        },
        {
          "id": "walk-south-3",
          "x": 64,
          "y": 0,
          "width": 32,
          "height": 32
        },
        {
          "id": "walk-south-4",
          "x": 96,
          "y": 0,
          "width": 32,
          "height": 32
        }
      ],
      "frame_digests": [
        "dbc4274b40ac3d522afa7fa14369a4fd43a4655b4251353b054b5c1513727602",
        "d2b5279309ab49a218f25d26179d72a5207baaad275a2c56d8dc86656a9a44f9",
        "f9f20e550780e3038944783c5ff8358bda911c5291a8254a9bdbba6c76028fc3",
        "478e9c058e52e84cf6c150aa596e43c13395a4a17ee54594e260501445a52095"
      ],
      "sheet_digest": "893606bb8c9be812b06736d84592a4c01d8fa7ea7bdafd6abcdfaea66a68d4e8",
      "phaser_load": {
        "key": "knight-walk-south",
        "url": "asset.svg",
        "svgConfig": {
          "width": 128,
          "height": 32
        }
      }
    },
    {
      "animation": "walk",
      "direction": "east",
      "timeline_id": "knight-walk-east",
      "flip": null,
      "frame_count": 4,
      "frame_rects": [
        {
          "id": "walk-east-1",
          "x": 0,
          "y": 0,
          "width": 32,
          "height": 32
        },
        {
          "id": "walk-east-2",
          "x": 32,
          "y": 0,
          "width": 32,
          "height": 32
        },
        {
          "id": "walk-east-3",
          "x": 64,
          "y": 0,
          "width": 32,
          "height": 32
        },
        {
          "id": "walk-east-4",
          "x": 96,
          "y": 0,
          "width": 32,
          "height": 32
        }
      ],
      "frame_digests": [
        "61941e3f4decbe504ad85d82f129695d9ca24ca7c73f2c3d5e11ea1fa0b96d7d",
        "1b4255afb24cac5e5040c7e303946541d13a36803f7f48b010ae7ee370d9d295",
        "e03734f2ee1e27b1266f4062fe808e55f410459f0e4d93f20b12af500f3a6473",
        "1b4255afb24cac5e5040c7e303946541d13a36803f7f48b010ae7ee370d9d295"
      ],
      "sheet_digest": "f173b2f24b0daa77243bf72719c95149ad55c05b454d1a1bca271e4d78ad443b",
      "phaser_load": {
        "key": "knight-walk-east",
        "url": "asset.svg",
        "svgConfig": {
          "width": 128,
          "height": 32
        }
      }
    },
    {
      "animation": "walk",
      "direction": "west",
      "timeline_id": "knight-walk-west",
      "flip": "horizontal",
      "frame_count": 4,
      "frame_rects": [
        {
          "id": "walk-west-1",
          "x": 0,
          "y": 0,
          "width": 32,
          "height": 32
        },
        {
          "id": "walk-west-2",
          "x": 32,
          "y": 0,
          "width": 32,
          "height": 32
        },
        {
          "id": "walk-west-3",
          "x": 64,
          "y": 0,
          "width": 32,
          "height": 32
        },
        {
          "id": "walk-west-4",
          "x": 96,
          "y": 0,
          "width": 32,
          "height": 32
        }
      ],
      "frame_digests": [
        "40de12b3734b51286b2229512ebe94541c5efa2bf42cae962ae9f729a9878748",
        "b83f6c265caf539c28c6bb4bf335206a526a32e598c1a1e1d36370b9b0bd6aa1",
        "796d511e97e2a66d6fdc6683de6bbe7e17729ea535997e13a64a25f56995f7ea",
        "b83f6c265caf539c28c6bb4bf335206a526a32e598c1a1e1d36370b9b0bd6aa1"
      ],
      "sheet_digest": "599973ebb46c9fec646413442cfda6255673bfbf6b548174fa666056403539ce",
      "phaser_load": {
        "key": "knight-walk-west",
        "url": "asset.svg",
        "svgConfig": {
          "width": 128,
          "height": 32
        }
      }
    }
  ],
  "manifest_digest": "795b3ab987367494c8c209278b479bcad0a522f8deaa962e18488bef86bacf27"
}
